[
    {
        "TABL_FRow": 1,
        "TABL_FID": 2,
        "TABL_FLang": "fa ",
        "TABL_FFieldName": "TGO_FName",
        "TABL_FFieldTitle": "نام کالا",
        "TABL_FFiltrable": 0,
        "TABL_FSortable": 0,
        "TABL_FDefaultWidth": 0,
        "TABL_FOrder": 0,
        "TABL_FID_Table": 11201,
        "TABL_FDefault": 1,
        "TABL_Table": "کالا و خدمات",
        "TABL_FID_FieldType": 11302,
        "TABL_FieldType": "عنوان",
        "TABL_FID_RelatedDefault": null,
        "TABL_RelatedDefault": "",
        "TABL_FID_User": null
    },
    {
        "TABL_FRow": 2,
        "TABL_FID": 3,
        "TABL_FLang": "fa ",
        "TABL_FFieldName": "TGO_FTag",
        "TABL_FFieldTitle": "عنوان کالا",
        "TABL_FFiltrable": 0,
        "TABL_FSortable": 0,
        "TABL_FDefaultWidth": 0,
        "TABL_FOrder": 1,
        "TABL_FID_Table": 11201,
        "TABL_FDefault": 1,
        "TABL_Table": "کالا و خدمات",
        "TABL_FID_FieldType": 11301,
        "TABL_FieldType": "متن ساده",
        "TABL_FID_RelatedDefault": null,
        "TABL_RelatedDefault": "",
        "TABL_FID_User": null
    },
    {
        "TABL_FRow": 3,
        "TABL_FID": 4,
        "TABL_FLang": "fa ",
        "TABL_FFieldName": "TGO_FID_Category1",
        "TABL_FFieldTitle": "گروه کالا",
        "TABL_FFiltrable": 0,
        "TABL_FSortable": 0,
        "TABL_FDefaultWidth": 0,
        "TABL_FOrder": 2,
        "TABL_FID_Table": 11201,
        "TABL_FDefault": 1,
        "TABL_Table": "کالا و خدمات",
        "TABL_FID_FieldType": 11309,
        "TABL_FieldType": "چند انتخابی",
        "TABL_FID_RelatedDefault": 272,
        "TABL_RelatedDefault": "گروه کالا",
        "TABL_FID_User": null
    },
    {
        "TABL_FRow": 4,
        "TABL_FID": 5,
        "TABL_FLang": "fa ",
        "TABL_FFieldName": "TGO_FID_TypeName",
        "TABL_FFieldTitle": "نوع کالا",
        "TABL_FFiltrable": 0,
        "TABL_FSortable": 0,
        "TABL_FDefaultWidth": 0,
        "TABL_FOrder": 3,
        "TABL_FID_Table": 11201,
        "TABL_FDefault": 0,
        "TABL_Table": "کالا و خدمات",
        "TABL_FID_FieldType": 11301,
        "TABL_FieldType": "متن ساده",
        "TABL_FID_RelatedDefault": 207,
        "TABL_RelatedDefault": "نوع کالا/خدمات",
        "TABL_FID_User": null
    },
    {
        "TABL_FRow": 5,
        "TABL_FID": 6,
        "TABL_FLang": "fa ",
        "TABL_FFieldName": "TGO_FID_UnitName",
        "TABL_FFieldTitle": "واحد اصلی",
        "TABL_FFiltrable": 0,
        "TABL_FSortable": 0,
        "TABL_FDefaultWidth": 0,
        "TABL_FOrder": 4,
        "TABL_FID_Table": 11201,
        "TABL_FDefault": 0,
        "TABL_Table": "کالا و خدمات",
        "TABL_FID_FieldType": 11301,
        "TABL_FieldType": "متن ساده",
        "TABL_FID_RelatedDefault": 206,
        "TABL_RelatedDefault": "واحد کالا",
        "TABL_FID_User": null
    },
    {
        "TABL_FRow": 6,
        "TABL_FID": 7,
        "TABL_FLang": "fa ",
        "TABL_FFieldName": "TGO_FID_Unit2Name",
        "TABL_FFieldTitle": "واحد فرعی",
        "TABL_FFiltrable": 0,
        "TABL_FSortable": 0,
        "TABL_FDefaultWidth": 0,
        "TABL_FOrder": 5,
        "TABL_FID_Table": 11201,
        "TABL_FDefault": 0,
        "TABL_Table": "کالا و خدمات",
        "TABL_FID_FieldType": 11301,
        "TABL_FieldType": "متن ساده",
        "TABL_FID_RelatedDefault": 206,
        "TABL_RelatedDefault": "واحد کالا",
        "TABL_FID_User": null
    },
    {
        "TABL_FRow": 7,
        "TABL_FID": 8,
        "TABL_FLang": "fa ",
        "TABL_FFieldName": "TGO_FCountINUnit",
        "TABL_FFieldTitle": "تعداد در واحد فرعی",
        "TABL_FFiltrable": 0,
        "TABL_FSortable": 0,
        "TABL_FDefaultWidth": 0,
        "TABL_FOrder": 6,
        "TABL_FID_Table": 11201,
        "TABL_FDefault": 0,
        "TABL_Table": "کالا و خدمات",
        "TABL_FID_FieldType": 11310,
        "TABL_FieldType": "عدد",
        "TABL_FID_RelatedDefault": null,
        "TABL_RelatedDefault": "",
        "TABL_FID_User": null
    },
    {
        "TABL_FRow": 8,
        "TABL_FID": 9,
        "TABL_FLang": "fa ",
        "TABL_FFieldName": "TGO_FID_TypeBox",
        "TABL_FFieldTitle": "بسته بندی",
        "TABL_FFiltrable": 0,
        "TABL_FSortable": 0,
        "TABL_FDefaultWidth": 0,
        "TABL_FOrder": 7,
        "TABL_FID_Table": 11201,
        "TABL_FDefault": 0,
        "TABL_Table": "کالا و خدمات",
        "TABL_FID_FieldType": 11309,
        "TABL_FieldType": "چند انتخابی",
        "TABL_FID_RelatedDefault": 227,
        "TABL_RelatedDefault": "انواع بسته بندی",
        "TABL_FID_User": null
    },
    {
        "TABL_FRow": 9,
        "TABL_FID": 10,
        "TABL_FLang": "fa ",
        "TABL_FFieldName": "TGO_FCountINBox",
        "TABL_FFieldTitle": "تعداد در بسته بندی",
        "TABL_FFiltrable": 0,
        "TABL_FSortable": 0,
        "TABL_FDefaultWidth": 0,
        "TABL_FOrder": 8,
        "TABL_FID_Table": 11201,
        "TABL_FDefault": 0,
        "TABL_Table": "کالا و خدمات",
        "TABL_FID_FieldType": 11310,
        "TABL_FieldType": "عدد",
        "TABL_FID_RelatedDefault": null,
        "TABL_RelatedDefault": "",
        "TABL_FID_User": null
    },
    {
        "TABL_FRow": 10,
        "TABL_FID": 11,
        "TABL_FLang": "fa ",
        "TABL_FFieldName": "TGO_FProductionTime",
        "TABL_FFieldTitle": "زمان تولید",
        "TABL_FFiltrable": 0,
        "TABL_FSortable": 0,
        "TABL_FDefaultWidth": 0,
        "TABL_FOrder": 9,
        "TABL_FID_Table": 11201,
        "TABL_FDefault": 0,
        "TABL_Table": "کالا و خدمات",
        "TABL_FID_FieldType": 11301,
        "TABL_FieldType": "متن ساده",
        "TABL_FID_RelatedDefault": null,
        "TABL_RelatedDefault": "",
        "TABL_FID_User": null
    },
    {
        "TABL_FRow": 11,
        "TABL_FID": 12,
        "TABL_FLang": "fa ",
        "TABL_FFieldName": "TGO_FID_TypeSale",
        "TABL_FFieldTitle": "مدیریت موجودی",
        "TABL_FFiltrable": 0,
        "TABL_FSortable": 0,
        "TABL_FDefaultWidth": 0,
        "TABL_FOrder": 10,
        "TABL_FID_Table": 11201,
        "TABL_FDefault": 0,
        "TABL_Table": "کالا و خدمات",
        "TABL_FID_FieldType": 11309,
        "TABL_FieldType": "چند انتخابی",
        "TABL_FID_RelatedDefault": 222,
        "TABL_RelatedDefault": "مدیریت موجودی",
        "TABL_FID_User": null
    },
    {
        "TABL_FRow": 12,
        "TABL_FID": 13,
        "TABL_FLang": "fa ",
        "TABL_FFieldName": "TGO_FSaleMin",
        "TABL_FFieldTitle": "حداقل تعداد فروش",
        "TABL_FFiltrable": 0,
        "TABL_FSortable": 0,
        "TABL_FDefaultWidth": 0,
        "TABL_FOrder": 11,
        "TABL_FID_Table": 11201,
        "TABL_FDefault": 0,
        "TABL_Table": "کالا و خدمات",
        "TABL_FID_FieldType": 11310,
        "TABL_FieldType": "عدد",
        "TABL_FID_RelatedDefault": null,
        "TABL_RelatedDefault": "",
        "TABL_FID_User": null
    },
    {
        "TABL_FRow": 13,
        "TABL_FID": 14,
        "TABL_FLang": "fa ",
        "TABL_FFieldName": "TGO_FBuyPoint",
        "TABL_FFieldTitle": "نقطه سفارش",
        "TABL_FFiltrable": 0,
        "TABL_FSortable": 0,
        "TABL_FDefaultWidth": 0,
        "TABL_FOrder": 12,
        "TABL_FID_Table": 11201,
        "TABL_FDefault": 0,
        "TABL_Table": "کالا و خدمات",
        "TABL_FID_FieldType": 11310,
        "TABL_FieldType": "عدد",
        "TABL_FID_RelatedDefault": null,
        "TABL_RelatedDefault": "",
        "TABL_FID_User": null
    },
    {
        "TABL_FRow": 14,
        "TABL_FID": 17,
        "TABL_FLang": "fa ",
        "TABL_FFieldName": "TGO_FSalePriceMax",
        "TABL_FFieldTitle": "قیمت فروش",
        "TABL_FFiltrable": 0,
        "TABL_FSortable": 0,
        "TABL_FDefaultWidth": 0,
        "TABL_FOrder": 13,
        "TABL_FID_Table": 11201,
        "TABL_FDefault": 0,
        "TABL_Table": "کالا و خدمات",
        "TABL_FID_FieldType": 11303,
        "TABL_FieldType": "قیمت",
        "TABL_FID_RelatedDefault": null,
        "TABL_RelatedDefault": "",
        "TABL_FID_User": null
    },
    {
        "TABL_FRow": 15,
        "TABL_FID": 18,
        "TABL_FLang": "fa ",
        "TABL_FFieldName": "TGO_FSalePriceMid",
        "TABL_FFieldTitle": "قیمت همکار",
        "TABL_FFiltrable": 0,
        "TABL_FSortable": 0,
        "TABL_FDefaultWidth": 0,
        "TABL_FOrder": 14,
        "TABL_FID_Table": 11201,
        "TABL_FDefault": 0,
        "TABL_Table": "کالا و خدمات",
        "TABL_FID_FieldType": 11303,
        "TABL_FieldType": "قیمت",
        "TABL_FID_RelatedDefault": null,
        "TABL_RelatedDefault": "",
        "TABL_FID_User": null
    },
    {
        "TABL_FRow": 16,
        "TABL_FID": 19,
        "TABL_FLang": "fa ",
        "TABL_FFieldName": "TGO_FSalePriceMin",
        "TABL_FFieldTitle": "قیمت نماینده",
        "TABL_FFiltrable": 0,
        "TABL_FSortable": 0,
        "TABL_FDefaultWidth": 0,
        "TABL_FOrder": 15,
        "TABL_FID_Table": 11201,
        "TABL_FDefault": 0,
        "TABL_Table": "کالا و خدمات",
        "TABL_FID_FieldType": 11303,
        "TABL_FieldType": "قیمت",
        "TABL_FID_RelatedDefault": null,
        "TABL_RelatedDefault": "",
        "TABL_FID_User": null
    },
    {
        "TABL_FRow": 17,
        "TABL_FID": 20,
        "TABL_FLang": "fa ",
        "TABL_FFieldName": "TGO_FBuyPrice",
        "TABL_FFieldTitle": "قیمت خرید",
        "TABL_FFiltrable": 0,
        "TABL_FSortable": 0,
        "TABL_FDefaultWidth": 0,
        "TABL_FOrder": 16,
        "TABL_FID_Table": 11201,
        "TABL_FDefault": 0,
        "TABL_Table": "کالا و خدمات",
        "TABL_FID_FieldType": 11303,
        "TABL_FieldType": "قیمت",
        "TABL_FID_RelatedDefault": null,
        "TABL_RelatedDefault": "",
        "TABL_FID_User": null
    },
    {
        "TABL_FRow": 18,
        "TABL_FID": 21,
        "TABL_FLang": "fa ",
        "TABL_FFieldName": "TGO_FSalePriceFix",
        "TABL_FFieldTitle": "مبلغ ثابت کلیشه",
        "TABL_FFiltrable": 0,
        "TABL_FSortable": 0,
        "TABL_FDefaultWidth": 0,
        "TABL_FOrder": 17,
        "TABL_FID_Table": 11201,
        "TABL_FDefault": 0,
        "TABL_Table": "کالا و خدمات",
        "TABL_FID_FieldType": 11303,
        "TABL_FieldType": "قیمت",
        "TABL_FID_RelatedDefault": null,
        "TABL_RelatedDefault": "",
        "TABL_FID_User": null
    },
    {
        "TABL_FRow": 19,
        "TABL_FID": 22,
        "TABL_FLang": "fa ",
        "TABL_FFieldName": "TGO_FBuyPercent",
        "TABL_FFieldTitle": "مبلغ ثابت فرم بندی",
        "TABL_FFiltrable": 0,
        "TABL_FSortable": 0,
        "TABL_FDefaultWidth": 0,
        "TABL_FOrder": 18,
        "TABL_FID_Table": 11201,
        "TABL_FDefault": 0,
        "TABL_Table": "کالا و خدمات",
        "TABL_FID_FieldType": 11303,
        "TABL_FieldType": "قیمت",
        "TABL_FID_RelatedDefault": null,
        "TABL_RelatedDefault": "",
        "TABL_FID_User": null
    },
    {
        "TABL_FRow": 20,
        "TABL_FID": 23,
        "TABL_FLang": "fa ",
        "TABL_FFieldName": "TGO_FID_Brand",
        "TABL_FFieldTitle": "نام برند",
        "TABL_FFiltrable": 0,
        "TABL_FSortable": 0,
        "TABL_FDefaultWidth": 0,
        "TABL_FOrder": 19,
        "TABL_FID_Table": 11201,
        "TABL_FDefault": 0,
        "TABL_Table": "کالا و خدمات",
        "TABL_FID_FieldType": 11301,
        "TABL_FieldType": "متن ساده",
        "TABL_FID_RelatedDefault": 223,
        "TABL_RelatedDefault": "برند",
        "TABL_FID_User": null
    },
    {
        "TABL_FRow": 21,
        "TABL_FID": 24,
        "TABL_FLang": "fa ",
        "TABL_FFieldName": "TGO_FBuyCode",
        "TABL_FFieldTitle": "کد خرید",
        "TABL_FFiltrable": 0,
        "TABL_FSortable": 0,
        "TABL_FDefaultWidth": 0,
        "TABL_FOrder": 20,
        "TABL_FID_Table": 11201,
        "TABL_FDefault": 0,
        "TABL_Table": "کالا و خدمات",
        "TABL_FID_FieldType": 11301,
        "TABL_FieldType": "متن ساده",
        "TABL_FID_RelatedDefault": null,
        "TABL_RelatedDefault": "",
        "TABL_FID_User": null
    },
    {
        "TABL_FRow": 22,
        "TABL_FID": 25,
        "TABL_FLang": "fa ",
        "TABL_FFieldName": "TGO_FCode",
        "TABL_FFieldTitle": "کد کالا",
        "TABL_FFiltrable": 0,
        "TABL_FSortable": 0,
        "TABL_FDefaultWidth": 0,
        "TABL_FOrder": 21,
        "TABL_FID_Table": 11201,
        "TABL_FDefault": 1,
        "TABL_Table": "کالا و خدمات",
        "TABL_FID_FieldType": 11301,
        "TABL_FieldType": "متن ساده",
        "TABL_FID_RelatedDefault": null,
        "TABL_RelatedDefault": "",
        "TABL_FID_User": null
    },
    {
        "TABL_FRow": 23,
        "TABL_FID": 26,
        "TABL_FLang": "fa ",
        "TABL_FFieldName": "TGO_FBuyLastDate",
        "TABL_FFieldTitle": "تاریخ تغییر قیمت خرید",
        "TABL_FFiltrable": 0,
        "TABL_FSortable": 0,
        "TABL_FDefaultWidth": 0,
        "TABL_FOrder": 22,
        "TABL_FID_Table": 11201,
        "TABL_FDefault": 0,
        "TABL_Table": "کالا و خدمات",
        "TABL_FID_FieldType": 11312,
        "TABL_FieldType": "تاریخ",
        "TABL_FID_RelatedDefault": null,
        "TABL_RelatedDefault": "",
        "TABL_FID_User": null
    },
    {
        "TABL_FRow": 24,
        "TABL_FID": 27,
        "TABL_FLang": "fa ",
        "TABL_FFieldName": "TGO_FSaleLastDate",
        "TABL_FFieldTitle": "تاریخ تغییر قیمت فروش",
        "TABL_FFiltrable": 0,
        "TABL_FSortable": 0,
        "TABL_FDefaultWidth": 0,
        "TABL_FOrder": 23,
        "TABL_FID_Table": 11201,
        "TABL_FDefault": 0,
        "TABL_Table": "کالا و خدمات",
        "TABL_FID_FieldType": 11312,
        "TABL_FieldType": "تاریخ",
        "TABL_FID_RelatedDefault": null,
        "TABL_RelatedDefault": "",
        "TABL_FID_User": null
    },
    {
        "TABL_FRow": 25,
        "TABL_FID": 28,
        "TABL_FLang": "fa ",
        "TABL_FFieldName": "TGO_FComment",
        "TABL_FFieldTitle": "شرح کالا",
        "TABL_FFiltrable": 0,
        "TABL_FSortable": 0,
        "TABL_FDefaultWidth": 0,
        "TABL_FOrder": 24,
        "TABL_FID_Table": 11201,
        "TABL_FDefault": 0,
        "TABL_Table": "کالا و خدمات",
        "TABL_FID_FieldType": 11301,
        "TABL_FieldType": "متن ساده",
        "TABL_FID_RelatedDefault": null,
        "TABL_RelatedDefault": "",
        "TABL_FID_User": null
    },
    {
        "TABL_FRow": 26,
        "TABL_FID": 29,
        "TABL_FLang": "fa ",
        "TABL_FFieldName": "TGO_FActive",
        "TABL_FFieldTitle": "فعال",
        "TABL_FFiltrable": 0,
        "TABL_FSortable": 0,
        "TABL_FDefaultWidth": 0,
        "TABL_FOrder": 25,
        "TABL_FID_Table": 11201,
        "TABL_FDefault": 0,
        "TABL_Table": "کالا و خدمات",
        "TABL_FID_FieldType": 11308,
        "TABL_FieldType": "تیک",
        "TABL_FID_RelatedDefault": null,
        "TABL_RelatedDefault": "",
        "TABL_FID_User": null
    },
    {
        "TABL_FRow": 27,
        "TABL_FID": 30,
        "TABL_FLang": "fa ",
        "TABL_FFieldName": "TGO_FCanSale",
        "TABL_FFieldTitle": "امکان فروش",
        "TABL_FFiltrable": 0,
        "TABL_FSortable": 0,
        "TABL_FDefaultWidth": 0,
        "TABL_FOrder": 26,
        "TABL_FID_Table": 11201,
        "TABL_FDefault": 0,
        "TABL_Table": "کالا و خدمات",
        "TABL_FID_FieldType": 11308,
        "TABL_FieldType": "تیک",
        "TABL_FID_RelatedDefault": null,
        "TABL_RelatedDefault": "",
        "TABL_FID_User": null
    },
    {
        "TABL_FRow": 28,
        "TABL_FID": 31,
        "TABL_FLang": "fa ",
        "TABL_FFieldName": "TGO_FArchive",
        "TABL_FFieldTitle": "امکان نمایش در محصولات",
        "TABL_FFiltrable": 0,
        "TABL_FSortable": 0,
        "TABL_FDefaultWidth": 0,
        "TABL_FOrder": 27,
        "TABL_FID_Table": 11201,
        "TABL_FDefault": 0,
        "TABL_Table": "کالا و خدمات",
        "TABL_FID_FieldType": 11308,
        "TABL_FieldType": "تیک",
        "TABL_FID_RelatedDefault": null,
        "TABL_RelatedDefault": "",
        "TABL_FID_User": null
    },
    {
        "TABL_FRow": 29,
        "TABL_FID": 32,
        "TABL_FLang": "fa ",
        "TABL_FFieldName": "TGO_FCanChangePrice",
        "TABL_FFieldTitle": "امکان تغییر قیمت",
        "TABL_FFiltrable": 0,
        "TABL_FSortable": 0,
        "TABL_FDefaultWidth": 0,
        "TABL_FOrder": 28,
        "TABL_FID_Table": 11201,
        "TABL_FDefault": 0,
        "TABL_Table": "کالا و خدمات",
        "TABL_FID_FieldType": 11308,
        "TABL_FieldType": "تیک",
        "TABL_FID_RelatedDefault": null,
        "TABL_RelatedDefault": "",
        "TABL_FID_User": null
    },
    {
        "TABL_FRow": 30,
        "TABL_FID": 33,
        "TABL_FLang": "fa ",
        "TABL_FFieldName": "TGO_FCanOff",
        "TABL_FFieldTitle": "امکان اعمال تخفیف",
        "TABL_FFiltrable": 0,
        "TABL_FSortable": 0,
        "TABL_FDefaultWidth": 0,
        "TABL_FOrder": 29,
        "TABL_FID_Table": 11201,
        "TABL_FDefault": 0,
        "TABL_Table": "کالا و خدمات",
        "TABL_FID_FieldType": 11308,
        "TABL_FieldType": "تیک",
        "TABL_FID_RelatedDefault": null,
        "TABL_RelatedDefault": "",
        "TABL_FID_User": null
    },
    {
        "TABL_FRow": 31,
        "TABL_FID": 34,
        "TABL_FLang": "fa ",
        "TABL_FFieldName": "TGO_FCanTax",
        "TABL_FFieldTitle": "ارزش افزوده",
        "TABL_FFiltrable": 0,
        "TABL_FSortable": 0,
        "TABL_FDefaultWidth": 0,
        "TABL_FOrder": 30,
        "TABL_FID_Table": 11201,
        "TABL_FDefault": 0,
        "TABL_Table": "کالا و خدمات",
        "TABL_FID_FieldType": 11308,
        "TABL_FieldType": "تیک",
        "TABL_FID_RelatedDefault": null,
        "TABL_RelatedDefault": "",
        "TABL_FID_User": null
    },
    {
        "TABL_FRow": 32,
        "TABL_FID": 35,
        "TABL_FLang": "fa ",
        "TABL_FFieldName": "TGO_FID",
        "TABL_FFieldTitle": "سريال",
        "TABL_FFiltrable": 0,
        "TABL_FSortable": 0,
        "TABL_FDefaultWidth": 0,
        "TABL_FOrder": 31,
        "TABL_FID_Table": 11201,
        "TABL_FDefault": 1,
        "TABL_Table": "کالا و خدمات",
        "TABL_FID_FieldType": 11311,
        "TABL_FieldType": "شناسه",
        "TABL_FID_RelatedDefault": null,
        "TABL_RelatedDefault": "",
        "TABL_FID_User": null
    },
    {
        "TABL_FRow": 33,
        "TABL_FID": 36,
        "TABL_FLang": "fa ",
        "TABL_FFieldName": "TGO_FDateReg",
        "TABL_FFieldTitle": "تاریخ ثبت",
        "TABL_FFiltrable": 0,
        "TABL_FSortable": 0,
        "TABL_FDefaultWidth": 0,
        "TABL_FOrder": 32,
        "TABL_FID_Table": 11201,
        "TABL_FDefault": 1,
        "TABL_Table": "کالا و خدمات",
        "TABL_FID_FieldType": 11312,
        "TABL_FieldType": "تاریخ",
        "TABL_FID_RelatedDefault": null,
        "TABL_RelatedDefault": "",
        "TABL_FID_User": null
    },
    {
        "TABL_FRow": 34,
        "TABL_FID": 37,
        "TABL_FLang": "fa ",
        "TABL_FFieldName": "TGO_FUserRegName",
        "TABL_FFieldTitle": "کاربر ثبت",
        "TABL_FFiltrable": 0,
        "TABL_FSortable": 0,
        "TABL_FDefaultWidth": 0,
        "TABL_FOrder": 33,
        "TABL_FID_Table": 11201,
        "TABL_FDefault": 0,
        "TABL_Table": "کالا و خدمات",
        "TABL_FID_FieldType": 11301,
        "TABL_FieldType": "متن ساده",
        "TABL_FID_RelatedDefault": null,
        "TABL_RelatedDefault": "",
        "TABL_FID_User": null
    }
]